Workbook

Sheet Dashboard
B2: Sales Case Study Interactive Dashboard
B3: Monthly, annual, day-of-week, and price elasticity summaries are calculated automatically, with charts displayed below.

Sheet Daily Metrics
A1: Date | B1: Sales (R) | C1: Cost of Sales (R) | D1: Quantity Sold | E1: Price per Unit (R) | F1: Gross Profit % | G1: GP per Unit (R) | H1: GP per Unit % | I1: Year-Month | J1: Year | K1: DOW Num | L1: Day of Week
A2: 41638 | B2: 223937.97 | C2: 230079.62 | D2: 6827 | E2: =B2/D2 -> 32.801812 | F2: =(B2-C2)/B2 -> -0.027425675 | G2: =(B2-C2)/D2 -> -0.89961184 | H2: =G2/E2 -> -0.027425675 | I2: =TEXT(A2,"yyyy-mm") -> 2013-12 | J2: =YEAR(A2) -> 2013 | K2: =WEEKDAY(A2,1) -> 2 | L2: =TEXT(A2,"ddd") -> Mon
A3: 41639 | B3: 300345.48 | C3: 306986.12 | D3: 9268 | E3: =B3/D3 -> 32.40672 | F3: =(B3-C3)/B3 -> -0.022110005 | G3: =(B3-C3)/D3 -> -0.71651273 | H3: =G3/E3 -> -0.022110005 | I3: =TEXT(A3,"yyyy-mm") -> 2013-12 | J3: =YEAR(A3) -> 2013 | K3: =WEEKDAY(A3,1) -> 3 | L3: =TEXT(A3,"ddd") -> Tue
A4: 41640 | B4: 86782.47 | C4: 87986.32 | D4: 2678 | E4: =B4/D4 -> 32.405702 | F4: =(B4-C4)/B4 -> -0.013872041 | G4: =(B4-C4)/D4 -> -0.44953323 | H4: =G4/E4 -> -0.013872041 | I4: =TEXT(A4,"yyyy-mm") -> 2014-01 | J4: =YEAR(A4) -> 2014 | K4: =WEEKDAY(A4,1) -> 4 | L4: =TEXT(A4,"ddd") -> Wed
A5: 41641 | B5: 200173.12 | C5: 202881.18 | D5: 6175 | E5: =B5/D5 -> 32.4167 | F5: =(B5-C5)/B5 -> -0.01352859 | G5: =(B5-C5)/D5 -> -0.43855223 | H5: =G5/E5 -> -0.01352859 | I5: =TEXT(A5,"yyyy-mm") -> 2014-01 | J5: =YEAR(A5) -> 2014 | K5: =WEEKDAY(A5,1) -> 5 | L5: =TEXT(A5,"ddd") -> Thu
A6: 41642 | B6: 326906.07 | C6: 333806.29 | D6: 10084 | E6: =B6/D6 -> 32.418293 | F6: =(B6-C6)/B6 -> -0.021107653 | G6: =(B6-C6)/D6 -> -0.6842741 | H6: =G6/E6 -> -0.021107653 | I6: =TEXT(A6,"yyyy-mm") -> 2014-01 | J6: =YEAR(A6) -> 2014 | K6: =WEEKDAY(A6,1) -> 6 | L6: =TEXT(A6,"ddd") -> Fri
A7: 41643 | B7: 307043.94 | C7: 313652.35 | D7: 9470 | E7: =B7/D7 -> 32.422803 | F7: =(B7-C7)/B7 -> -0.021522685 | G7: =(B7-C7)/D7 -> -0.69782577 | H7: =G7/E7 -> -0.021522685 | I7: =TEXT(A7,"yyyy-mm") -> 2014-01 | J7: =YEAR(A7) -> 2014 | K7: =WEEKDAY(A7,1) -> 7 | L7: =TEXT(A7,"ddd") -> Sat
A8: 41644 | B8: 179188.88 | C8: 183083.28 | D8: 5524 | E8: =B8/D8 -> 32.438248 | F8: =(B8-C8)/B8 -> -0.021733492 | G8: =(B8-C8)/D8 -> -0.70499638 | H8: =G8/E8 -> -0.021733492 | I8: =TEXT(A8,"yyyy-mm") -> 2014-01 | J8: =YEAR(A8) -> 2014 | K8: =WEEKDAY(A8,1) -> 1 | L8: =TEXT(A8,"ddd") -> Sun
A9: 41645 | B9: 306351.95 | C9: 313446.07 | D9: 9448 | E9: =B9/D9 -> 32.425058 | F9: =(B9-C9)/B9 -> -0.023156765 | G9: =(B9-C9)/D9 -> -0.75085944 | H9: =G9/E9 -> -0.023156765 | I9: =TEXT(A9,"yyyy-mm") -> 2014-01 | J9: =YEAR(A9) -> 2014 | K9: =WEEKDAY(A9,1) -> 2 | L9: =TEXT(A9,"ddd") -> Mon
A10: 41646 | B10: 224020.41 | C10: 229533.97 | D10: 6911 | E10: =B10/D10 -> 32.41505 | F10: =(B10-C10)/B10 -> -0.024611865 | G10: =(B10-C10)/D10 -> -0.79779482 | H10: =G10/E10 -> -0.024611865 | I10: =TEXT(A10,"yyyy-mm") -> 2014-01 | J10: =YEAR(A10) -> 2014 | K10: =WEEKDAY(A10,1) -> 3 | L10: =TEXT(A10,"ddd") -> Tue
A11: 41647 | B11: 101836.4 | C11: 99381.97 | D11: 2990 | E11: =B11/D11 -> 34.058997 | F11: =(B11-C11)/B11 -> 0.024101696 | G11: =(B11-C11)/D11 -> 0.8208796 | H11: =G11/E11 -> 0.024101696 | I11: =TEXT(A11,"yyyy-mm") -> 2014-01 | J11: =YEAR(A11) -> 2014 | K11: =WEEKDAY(A11,1) -> 4 | L11: =TEXT(A11,"ddd") -> Wed
A12: 41648 | B12: 107804.3 | C12: 104816.46 | D12: 3159 | E12: =B12/D12 -> 34.126084 | F12: =(B12-C12)/B12 -> 0.027715407 | G12: =(B12-C12)/D12 -> 0.9458183 | H12: =G12/E12 -> 0.027715407 | I12: =TEXT(A12,"yyyy-mm") -> 2014-01 | J12: =YEAR(A12) -> 2014 | K12: =WEEKDAY(A12,1) -> 5 | L12: =TEXT(A12,"ddd") -> Thu
A13: 41649 | B13: 144829.96 | C13: 141334 | D13: 4246 | E13: =B13/D13 -> 34.109741 | F13: =(B13-C13)/B13 -> 0.024138376 | G13: =(B13-C13)/D13 -> 0.82335374 | H13: =G13/E13 -> 0.024138376 | I13: =TEXT(A13,"yyyy-mm") -> 2014-01 | J13: =YEAR(A13) -> 2014 | K13: =WEEKDAY(A13,1) -> 6 | L13: =TEXT(A13,"ddd") -> Fri
... A1054: 42690 | B1054: 77229.97 | C1054: 71428.87 | D1054: 1763 | E1054: =B1054/D1054 -> 43.805995 | F1054: =(B1054-C1054)/B1054 -> 0.075114622 | G1054: =(B1054-C1054)/D1054 -> 3.2904708 | H1054: =G1054/E1054 -> 0.075114622 | I1054: =TEXT(A1054,"yyyy-mm") -> 2016-11 | J1054: =YEAR(A1054) -> 2016 | K1054: =WEEKDAY(A1054,1) -> 4 | L1054: =TEXT(A1054,"ddd") -> Wed

Sheet Monthly Summary
A1: Month | B1: Total Sales (R) | C1: Total Cost of Sales (R) | D1: Total Gross Profit (R) | E1: GP % | F1: Total Units Sold
A2: 2013-12 | B2: =SUMIFS('Daily Metrics'!$B$2:$B$1054,'Daily Metrics'!$I$2:$I$1054,A2) -> 524283.45 | C2: =SUMIFS('Daily Metrics'!$C$2:$C$1054,'Daily Metrics'!$I$2:$I$1054,A2) -> 537065.74 | D2: =B2-C2 -> -12782.29 | E2: =D2/B2 -> -0.024380495 | F2: =SUMIFS('Daily Metrics'!$D$2:$D$1054,'Daily Metrics'!$I$2:$I$1054,A2) -> 16095
A3: 2014-01 | B3: =SUMIFS('Daily Metrics'!$B$2:$B$1054,'Daily Metrics'!$I$2:$I$1054,A3) -> 4008180.5 | C3: =SUMIFS('Daily Metrics'!$C$2:$C$1054,'Daily Metrics'!$I$2:$I$1054,A3) -> 3995719.9 | D3: =B3-C3 -> 12460.59 | E3: =D3/B3 -> 0.0031087897 | F3: =SUMIFS('Daily Metrics'!$D$2:$D$1054,'Daily Metrics'!$I$2:$I$1054,A3) -> 119965
A4: 2014-02 | B4: =SUMIFS('Daily Metrics'!$B$2:$B$1054,'Daily Metrics'!$I$2:$I$1054,A4) -> 5780487.2 | C4: =SUMIFS('Daily Metrics'!$C$2:$C$1054,'Daily Metrics'!$I$2:$I$1054,A4) -> 5913478.5 | D4: =B4-C4 -> -132991.36 | E4: =D4/B4 -> -0.023006947 | F4: =SUMIFS('Daily Metrics'!$D$2:$D$1054,'Daily Metrics'!$I$2:$I$1054,A4) -> 178035
A5: 2014-03 | B5: =SUMIFS('Daily Metrics'!$B$2:$B$1054,'Daily Metrics'!$I$2:$I$1054,A5) -> 8279517.2 | C5: =SUMIFS('Daily Metrics'!$C$2:$C$1054,'Daily Metrics'!$I$2:$I$1054,A5) -> 8415654 | D5: =B5-C5 -> -136136.87 | E5: =D5/B5 -> -0.01644261 | F5: =SUMIFS('Daily Metrics'!$D$2:$D$1054,'Daily Metrics'!$I$2:$I$1054,A5) -> 252836
A6: 2014-04 | B6: =SUMIFS('Daily Metrics'!$B$2:$B$1054,'Daily Metrics'!$I$2:$I$1054,A6) -> 6435743.3 | C6: =SUMIFS('Daily Metrics'!$C$2:$C$1054,'Daily Metrics'!$I$2:$I$1054,A6) -> 6479643.6 | D6: =B6-C6 -> -43900.3 | E6: =D6/B6 -> -0.0068213255 | F6: =SUMIFS('Daily Metrics'!$D$2:$D$1054,'Daily Metrics'!$I$2:$I$1054,A6) -> 190091
A7: 2014-05 | B7: =SUMIFS('Daily Metrics'!$B$2:$B$1054,'Daily Metrics'!$I$2:$I$1054,A7) -> 7694906.2 | C7: =SUMIFS('Daily Metrics'!$C$2:$C$1054,'Daily Metrics'!$I$2:$I$1054,A7) -> 8017240.4 | D7: =B7-C7 -> -322334.28 | E7: =D7/B7 -> -0.041889306 | F7: =SUMIFS('Daily Metrics'!$D$2:$D$1054,'Daily Metrics'!$I$2:$I$1054,A7) -> 235793
A8: 2014-06 | B8: =SUMIFS('Daily Metrics'!$B$2:$B$1054,'Daily Metrics'!$I$2:$I$1054,A8) -> 6456943.6 | C8: =SUMIFS('Daily Metrics'!$C$2:$C$1054,'Daily Metrics'!$I$2:$I$1054,A8) -> 6645843.7 | D8: =B8-C8 -> -188900.01 | E8: =D8/B8 -> -0.029255329 | F8: =SUMIFS('Daily Metrics'!$D$2:$D$1054,'Daily Metrics'!$I$2:$I$1054,A8) -> 198857
A9: 2014-07 | B9: =SUMIFS('Daily Metrics'!$B$2:$B$1054,'Daily Metrics'!$I$2:$I$1054,A9) -> 4933710.8 | C9: =SUMIFS('Daily Metrics'!$C$2:$C$1054,'Daily Metrics'!$I$2:$I$1054,A9) -> 5004894.9 | D9: =B9-C9 -> -71184.05 | E9: =D9/B9 -> -0.014428095 | F9: =SUMIFS('Daily Metrics'!$D$2:$D$1054,'Daily Metrics'!$I$2:$I$1054,A9) -> 147449
A10: 2014-08 | B10: =SUMIFS('Daily Metrics'!$B$2:$B$1054,'Daily Metrics'!$I$2:$I$1054,A10) -> 10010378 | C10: =SUMIFS('Daily Metrics'!$C$2:$C$1054,'Daily Metrics'!$I$2:$I$1054,A10) -> 10524432 | D10: =B10-C10 -> -514054.18 | E10: =D10/B10 -> -0.051352123 | F10: =SUMIFS('Daily Metrics'!$D$2:$D$1054,'Daily Metrics'!$I$2:$I$1054,A10) -> 310572
A11: 2014-09 | B11: =SUMIFS('Daily Metrics'!$B$2:$B$1054,'Daily Metrics'!$I$2:$I$1054,A11) -> 7643452.7 | C11: =SUMIFS('Daily Metrics'!$C$2:$C$1054,'Daily Metrics'!$I$2:$I$1054,A11) -> 8193560 | D11: =B11-C11 -> -550107.35 | E11: =D11/B11 -> -0.071971055 | F11: =SUMIFS('Daily Metrics'!$D$2:$D$1054,'Daily Metrics'!$I$2:$I$1054,A11) -> 237742
A12: 2014-10 | B12: =SUMIFS('Daily Metrics'!$B$2:$B$1054,'Daily Metrics'!$I$2:$I$1054,A12) -> 5924683.4 | C12: =SUMIFS('Daily Metrics'!$C$2:$C$1054,'Daily Metrics'!$I$2:$I$1054,A12) -> 6038461.3 | D12: =B12-C12 -> -113777.92 | E12: =D12/B12 -> -0.019204051 | F12: =SUMIFS('Daily Metrics'!$D$2:$D$1054,'Daily Metrics'!$I$2:$I$1054,A12) -> 171709
A13: 2014-11 | B13: =SUMIFS('Daily Metrics'!$B$2:$B$1054,'Daily Metrics'!$I$2:$I$1054,A13) -> 2631353.3 | C13: =SUMIFS('Daily Metrics'!$C$2:$C$1054,'Daily Metrics'!$I$2:$I$1054,A13) -> 2517124.8 | D13: =B13-C13 -> 114228.5 | E13: =D13/B13 -> 0.043410552 | F13: =SUMIFS('Daily Metrics'!$D$2:$D$1054,'Daily Metrics'!$I$2:$I$1054,A13) -> 68569
... A37: 2016-11 | B37: =SUMIFS('Daily Metrics'!$B$2:$B$1054,'Daily Metrics'!$I$2:$I$1054,A37) -> 1851029.9 | C37: =SUMIFS('Daily Metrics'!$C$2:$C$1054,'Daily Metrics'!$I$2:$I$1054,A37) -> 1724472.9 | D37: =B37-C37 -> 126556.97 | E37: =D37/B37 -> 0.068371112 | F37: =SUMIFS('Daily Metrics'!$D$2:$D$1054,'Daily Metrics'!$I$2:$I$1054,A37) -> 43107

Sheet Annual Summary
A1: Year | B1: Total Sales (R) | C1: Total Cost of Sales (R) | D1: Total Gross Profit (R) | E1: GP % | F1: Total Units Sold | G1: Avg Unit Price (R) | H1: Trading Days
A2: 2013 | B2: =SUMIFS('Daily Metrics'!$B$2:$B$1054,'Daily Metrics'!$J$2:$J$1054,A2) -> 524283.45 | C2: =SUMIFS('Daily Metrics'!$C$2:$C$1054,'Daily Metrics'!$J$2:$J$1054,A2) -> 537065.74 | D2: =B2-C2 -> -12782.29 | E2: =D2/B2 -> -0.024380495 | F2: =SUMIFS('Daily Metrics'!$D$2:$D$1054,'Daily Metrics'!$J$2:$J$1054,A2) -> 16095 | G2: =AVERAGEIFS('Daily Metrics'!$E$2:$E$1054,'Daily Metrics'!$J$2:$J$1054,A2) -> 32.604266 | H2: =COUNTIFS('Daily Metrics'!$J$2:$J$1054,A2) -> 2
A3: 2014 | B3: =SUMIFS('Daily Metrics'!$B$2:$B$1054,'Daily Metrics'!$J$2:$J$1054,A3) -> 75414976 | C3: =SUMIFS('Daily Metrics'!$C$2:$C$1054,'Daily Metrics'!$J$2:$J$1054,A3) -> 77680850 | D3: =B3-C3 -> -2265874 | E3: =D3/B3 -> -0.030045412 | F3: =SUMIFS('Daily Metrics'!$D$2:$D$1054,'Daily Metrics'!$J$2:$J$1054,A3) -> 2254230 | G3: =AVERAGEIFS('Daily Metrics'!$E$2:$E$1054,'Daily Metrics'!$J$2:$J$1054,A3) -> 34.573533 | H3: =COUNTIFS('Daily Metrics'!$J$2:$J$1054,A3) -> 365
A4: 2015 | B4: =SUMIFS('Daily Metrics'!$B$2:$B$1054,'Daily Metrics'!$J$2:$J$1054,A4) -> 64017593 | C4: =SUMIFS('Daily Metrics'!$C$2:$C$1054,'Daily Metrics'!$J$2:$J$1054,A4) -> 67917204 | D4: =B4-C4 -> -3899610.6 | E4: =D4/B4 -> -0.06091467 | F4: =SUMIFS('Daily Metrics'!$D$2:$D$1054,'Daily Metrics'!$J$2:$J$1054,A4) -> 1715089 | G4: =AVERAGEIFS('Daily Metrics'!$E$2:$E$1054,'Daily Metrics'!$J$2:$J$1054,A4) -> 38.327482 | H4: =COUNTIFS('Daily Metrics'!$J$2:$J$1054,A4) -> 365
A5: 2016 | B5: =SUMIFS('Daily Metrics'!$B$2:$B$1054,'Daily Metrics'!$J$2:$J$1054,A5) -> 46952976 | C5: =SUMIFS('Daily Metrics'!$C$2:$C$1054,'Daily Metrics'!$J$2:$J$1054,A5) -> 47890990 | D5: =B5-C5 -> -938014.57 | E5: =D5/B5 -> -0.019977745 | F5: =SUMIFS('Daily Metrics'!$D$2:$D$1054,'Daily Metrics'!$J$2:$J$1054,A5) -> 1294458 | G5: =AVERAGEIFS('Daily Metrics'!$E$2:$E$1054,'Daily Metrics'!$J$2:$J$1054,A5) -> 38.515993 | H5: =COUNTIFS('Daily Metrics'!$J$2:$J$1054,A5) -> 321

Sheet Day of Week Summary
A1: Day of Week | B1: DOW Num | C1: Avg Daily Sales (R) | D1: Avg Daily Qty | E1: Avg Unit Price (R)
A2: Sunday | B2: 1 | C2: =AVERAGEIFS('Daily Metrics'!$B$2:$B$1054,'Daily Metrics'!$K$2:$K$1054,B2) -> 138170.86 | D2: =AVERAGEIFS('Daily Metrics'!$D$2:$D$1054,'Daily Metrics'!$K$2:$K$1054,B2) -> 3897.1 | E2: =AVERAGEIFS('Daily Metrics'!$E$2:$E$1054,'Daily Metrics'!$K$2:$K$1054,B2) -> 37.015503
A3: Monday | B3: 2 | C3: =AVERAGEIFS('Daily Metrics'!$B$2:$B$1054,'Daily Metrics'!$K$2:$K$1054,B3) -> 156313.03 | D3: =AVERAGEIFS('Daily Metrics'!$D$2:$D$1054,'Daily Metrics'!$K$2:$K$1054,B3) -> 4400.0464 | E3: =AVERAGEIFS('Daily Metrics'!$E$2:$E$1054,'Daily Metrics'!$K$2:$K$1054,B3) -> 37.242813
A4: Tuesday | B4: 3 | C4: =AVERAGEIFS('Daily Metrics'!$B$2:$B$1054,'Daily Metrics'!$K$2:$K$1054,B4) -> 137314.86 | D4: =AVERAGEIFS('Daily Metrics'!$D$2:$D$1054,'Daily Metrics'!$K$2:$K$1054,B4) -> 3851.702 | E4: =AVERAGEIFS('Daily Metrics'!$E$2:$E$1054,'Daily Metrics'!$K$2:$K$1054,B4) -> 37.232696
A5: Wednesday | B5: 4 | C5: =AVERAGEIFS('Daily Metrics'!$B$2:$B$1054,'Daily Metrics'!$K$2:$K$1054,B5) -> 145890.66 | D5: =AVERAGEIFS('Daily Metrics'!$D$2:$D$1054,'Daily Metrics'!$K$2:$K$1054,B5) -> 4105.9934 | E5: =AVERAGEIFS('Daily Metrics'!$E$2:$E$1054,'Daily Metrics'!$K$2:$K$1054,B5) -> 37.015791
A6: Thursday | B6: 5 | C6: =AVERAGEIFS('Daily Metrics'!$B$2:$B$1054,'Daily Metrics'!$K$2:$K$1054,B6) -> 141084.76 | D6: =AVERAGEIFS('Daily Metrics'!$D$2:$D$1054,'Daily Metrics'!$K$2:$K$1054,B6) -> 3969.22 | E6: =AVERAGEIFS('Daily Metrics'!$E$2:$E$1054,'Daily Metrics'!$K$2:$K$1054,B6) -> 37.161422
A7: Friday | B7: 6 | C7: =AVERAGEIFS('Daily Metrics'!$B$2:$B$1054,'Daily Metrics'!$K$2:$K$1054,B7) -> 245313.97 | D7: =AVERAGEIFS('Daily Metrics'!$D$2:$D$1054,'Daily Metrics'!$K$2:$K$1054,B7) -> 6955.3933 | E7: =AVERAGEIFS('Daily Metrics'!$E$2:$E$1054,'Daily Metrics'!$K$2:$K$1054,B7) -> 36.982263
A8: Saturday | B8: 7 | C8: =AVERAGEIFS('Daily Metrics'!$B$2:$B$1054,'Daily Metrics'!$K$2:$K$1054,B8) -> 279047.26 | D8: =AVERAGEIFS('Daily Metrics'!$D$2:$D$1054,'Daily Metrics'!$K$2:$K$1054,B8) -> 7937.3067 | E8: =AVERAGEIFS('Daily Metrics'!$E$2:$E$1054,'Daily Metrics'!$K$2:$K$1054,B8) -> 36.857654

Sheet Elasticity
A1: Period | B1: Baseline Start | C1: Baseline End | D1: Promo Start | E1: Promo End | F1: Baseline Avg Price (R) | G1: Promo Avg Price (R) | H1: % Change Price | I1: Baseline Avg Qty | J1: Promo Avg Qty | K1: % Change Qty | L1: Price Elasticity of Demand
A2: Promo 1 | B2: 2016-01-04 | C2: 2016-01-21 | D2: 2016-01-22 | E2: 2016-02-08 | F2: =AVERAGEIFS('Daily Metrics'!$E$2:$E$1054,'Daily Metrics'!$A$2:$A$1054,">="&B2,'Daily Metrics'!$A$2:$A$1054,"<="&C2) -> 40.027069 | G2: =AVERAGEIFS('Daily Metrics'!$E$2:$E$1054,'Daily Metrics'!$A$2:$A$1054,">="&D2,'Daily Metrics'!$A$2:$A$1054,"<="&E2) -> 34.072824 | H2: =(G2-F2)/F2 -> -0.14875547 | I2: =AVERAGEIFS('Daily Metrics'!$D$2:$D$1054,'Daily Metrics'!$A$2:$A$1054,">="&B2,'Daily Metrics'!$A$2:$A$1054,"<="&C2) -> 3100.7778 | J2: =AVERAGEIFS('Daily Metrics'!$D$2:$D$1054,'Daily Metrics'!$A$2:$A$1054,">="&D2,'Daily Metrics'!$A$2:$A$1054,"<="&E2) -> 7925.1111 | K2: =(J2-I2)/I2 -> 1.5558462 | L2: =K2/H2 -> -10.459086
A3: Promo 2 | B3: 2015-09-09 | C3: 2015-09-22 | D3: 2015-09-23 | E3: 2015-10-06 | F3: =AVERAGEIFS('Daily Metrics'!$E$2:$E$1054,'Daily Metrics'!$A$2:$A$1054,">="&B3,'Daily Metrics'!$A$2:$A$1054,"<="&C3) -> 39.137514 | G3: =AVERAGEIFS('Daily Metrics'!$E$2:$E$1054,'Daily Metrics'!$A$2:$A$1054,">="&D3,'Daily Metrics'!$A$2:$A$1054,"<="&E3) -> 33.396349 | H3: =(G3-F3)/F3 -> -0.14669211 | I3: =AVERAGEIFS('Daily Metrics'!$D$2:$D$1054,'Daily Metrics'!$A$2:$A$1054,">="&B3,'Daily Metrics'!$A$2:$A$1054,"<="&C3) -> 1339.4286 | J3: =AVERAGEIFS('Daily Metrics'!$D$2:$D$1054,'Daily Metrics'!$A$2:$A$1054,">="&D3,'Daily Metrics'!$A$2:$A$1054,"<="&E3) -> 8089.3571 | K3: =(J3-I3)/I3 -> 5.0394091 | L3: =K3/H3 -> -34.353647
A4: Promo 3 | B4: 2016-06-17 | C4: 2016-06-26 | D4: 2016-06-27 | E4: 2016-07-06 | F4: =AVERAGEIFS('Daily Metrics'!$E$2:$E$1054,'Daily Metrics'!$A$2:$A$1054,">="&B4,'Daily Metrics'!$A$2:$A$1054,"<="&C4) -> 35.033053 | G4: =AVERAGEIFS('Daily Metrics'!$E$2:$E$1054,'Daily Metrics'!$A$2:$A$1054,">="&D4,'Daily Metrics'!$A$2:$A$1054,"<="&E4) -> 33.386901 | H4: =(G4-F4)/F4 -> -0.046988543 | I4: =AVERAGEIFS('Daily Metrics'!$D$2:$D$1054,'Daily Metrics'!$A$2:$A$1054,">="&B4,'Daily Metrics'!$A$2:$A$1054,"<="&C4) -> 6719.3 | J4: =AVERAGEIFS('Daily Metrics'!$D$2:$D$1054,'Daily Metrics'!$A$2:$A$1054,">="&D4,'Daily Metrics'!$A$2:$A$1054,"<="&E4) -> 8474.5 | K4: =(J4-I4)/I4 -> 0.26121769 | L4: =K4/H4 -> -5.5591783

Sheet KPI Summary
A1: Metric | B1: Value
A2: Total Sales (R) | B2: =SUM('Daily Metrics'!$B$2:$B$1054) -> 1.8690983e+08
A3: Total Cost of Sales (R) | B3: =SUM('Daily Metrics'!$C$2:$C$1054) -> 1.9402611e+08
A4: Total Gross Profit (R) | B4: =B2-B3 -> -7116281.5
A5: Overall GP % | B5: =B4/B2 -> -0.03807334
A6: Total Units Sold | B6: =SUM('Daily Metrics'!$D$2:$D$1054) -> 5279872
A7: Avg Daily Unit Price (R) | B7: =AVERAGE('Daily Metrics'!$E$2:$E$1054) -> 37.072852
A8: Volume-Weighted Avg Unit Price (R) | B8: =B2/B6 -> 35.400447
A9: Total Trading Days | B9: =COUNT('Daily Metrics'!$A$2:$A$1054) -> 1053
A10: First Date | B10: =MIN('Daily Metrics'!$A$2:$A$1054) -> 41638
A11: Last Date | B11: =MAX('Daily Metrics'!$A$2:$A$1054) -> 42690
